slave/__init__.py
slave/__main__.py
slave/lib/bots.py
slave/lib/client.py
slave/playground/bots.py
slave_irc-1.1.1.dist-info/LICENSE
slave_irc-1.1.1.dist-info/METADATA
slave_irc-1.1.1.dist-info/WHEEL
slave_irc-1.1.1.dist-info/top_level.txt
slave_irc-1.1.1.dist-info/RECORD
