Metadata-Version: 2.1
Name: slave-irc
Version: 1.1.1
Summary: IRC based customizable botnet framework
Home-page: https://github.com/bufgix/slave
Author: bufgix
Author-email: ooruc471@yandex.com
License: MIT
Platform: UNKNOWN
Classifier: License :: OSI Approved :: MIT License
Classifier: Programming Language :: Python :: 3
Classifier: Programming Language :: Python :: 3.7
Requires-Dist: pyinstaller
Requires-Dist: mss
